powerline_hgstatus/__init__.py
powerline_hgstatus/segments.py
powerline_hgstatus-0.1.5.dist-info/DESCRIPTION.rst
powerline_hgstatus-0.1.5.dist-info/METADATA
powerline_hgstatus-0.1.5.dist-info/RECORD
powerline_hgstatus-0.1.5.dist-info/WHEEL
powerline_hgstatus-0.1.5.dist-info/metadata.json
powerline_hgstatus-0.1.5.dist-info/top_level.txt
