Metadata-Version: 2.0
Name: powerline-hgstatus
Version: 0.1.5
Summary: A Powerline segment for showing the status of a Mercurial working copy
Home-page: https://github.com/ischer/powerline-hgstatus
Author: Ian Scherer
Author-email: ianscherer@comcast.net
License: MIT
Keywords: powerline hg status prompt
Platform: UNKNOWN
Classifier: Environment :: Console
Classifier: Intended Audience :: Developers
Classifier: License :: OSI Approved :: MIT License
Classifier: Topic :: Terminals
